<?xml version="1.0"?>
<ApiLinks xmlns="https://github.com/HollowKnight-Modding/HollowKnight.ModLinks/HollowKnight.ModManager"
    xmlns:xsd="http://www.w3.org/2001/XMLSchema"
    xmlns:xsi="http://www.w3.org/2001/XMLSchema-instance"
    xsi:schemaLocation="https://github.com/HollowKnight-Modding/HollowKnight.ModLinks/HollowKnight.ModManager https://raw.githubusercontent.com/HollowKnight-Modding/HollowKnight.ModLinks/main/Schemas/ApiLinks.xml">
    <Manifest>
        <Version>74</Version>

        <Links>
            
            <Mac>
                <![CDATA[https://raw.githubusercontent.com/timothymarriott/modlinks-silksong/refs/heads/main/content/Api.zip]]>
            </Mac>
        </Links>

        <Files>
            
        </Files>
    </Manifest>
</ApiLinks>
